docs/.gitignore
docs/Makefile
docs/__init__.py
docs/api.rst
docs/audit.rst
docs/cataloging.rst
docs/cataloging.txt
docs/conf.py
docs/configuration.rst
docs/content.rst
docs/copyright.rst
docs/dump.rst
docs/evolution.rst
docs/folder_contents.rst
docs/forms.rst
docs/glossary.rst
docs/index.rst
docs/install.rst
docs/intro.rst
docs/locking.rst
docs/magic.rst
docs/mgmtview.rst
docs/permissions.rst
docs/references.rst
docs/remake
docs/retail.rst
docs/scripts.rst
docs/sdi.rst
docs/services.rst
docs/statistics.rst
docs/vrooting.rst
docs/workflows.rst
docs/_themes/.gitignore
docs/_themes/CHANGES.txt
docs/_themes/README.rst
docs/_themes/substanced_theme_support.py
docs/_themes/substanced/defindex.html
docs/_themes/substanced/domainindex.html
docs/_themes/substanced/genindex-single.html
docs/_themes/substanced/genindex-split.html
docs/_themes/substanced/genindex.html
docs/_themes/substanced/globaltoc.html
docs/_themes/substanced/layout.html
docs/_themes/substanced/localtoc.html
docs/_themes/substanced/page.html
docs/_themes/substanced/relations.html
docs/_themes/substanced/search.html
docs/_themes/substanced/searchbox.html
docs/_themes/substanced/searchresults.html
docs/_themes/substanced/sourcelink.html
docs/_themes/substanced/theme.conf
docs/_themes/substanced/changes/frameset.html
docs/_themes/substanced/changes/rstsource.html
docs/_themes/substanced/changes/versionchanges.html
docs/_themes/substanced/static/ajax-loader.gif
docs/_themes/substanced/static/basic.css_t
docs/_themes/substanced/static/capsule-icon-32.png
docs/_themes/substanced/static/cguardia.jpg
docs/_themes/substanced/static/comment-bright.png
docs/_themes/substanced/static/comment-close.png
docs/_themes/substanced/static/comment.png
docs/_themes/substanced/static/dialog-note.png
docs/_themes/substanced/static/dialog-seealso.png
docs/_themes/substanced/static/dialog-topic.png
docs/_themes/substanced/static/dialog-warning.png
docs/_themes/substanced/static/doctools.js
substanced-1.0.post1.dist-info/LICENSE.txt
substanced-1.0.post1.dist-info/METADATA
substanced-1.0.post1.dist-info/WHEEL
substanced-1.0.post1.dist-info/entry_points.txt
substanced-1.0.post1.dist-info/top_level.txt
substanced-1.0.post1.dist-info/RECORD
