Metadata-Version: 2.1
Name: substanced
Version: 1.0.post1
Summary: An application server built using Pyramid
Home-page: http://www.substanced.net/
Author: Chris McDonough
Author-email: pylons-devel@googlegroups.com
License: BSD-derived (http://www.repoze.org/LICENSE.txt)
Keywords: wsgi pylons pyramid zodb catalog zope
Platform: UNKNOWN
Classifier: Intended Audience :: Developers
Classifier: Programming Language :: Python
Classifier: Programming Language :: Python :: 2
Classifier: Programming Language :: Python :: 2.7
Classifier: Programming Language :: Python :: 3
Classifier: Programming Language :: Python :: 3.4
Classifier: Programming Language :: Python :: 3.5
Classifier: Programming Language :: Python :: Implementation :: CPython
Classifier: Framework :: Pyramid
Classifier: Topic :: Internet :: WWW/HTTP :: WSGI
Classifier: License :: Repoze Public License
Requires-Dist: pyramid (>=1.5dev)
Requires-Dist: ZODB
Requires-Dist: hypatia (>=0.2)
Requires-Dist: venusian (>=1.0a3)
Requires-Dist: deform (>=2.0a2)
Requires-Dist: colander (>=1.0a1)
Requires-Dist: pyramid-zodbconn (>=0.6)
Requires-Dist: pyramid-chameleon
Requires-Dist: pyramid-mailer
Requires-Dist: cryptacular
Requires-Dist: python-magic
Requires-Dist: PyYAML
Requires-Dist: zope.copy
Requires-Dist: zope.component
Requires-Dist: zope.deprecation
Requires-Dist: statsd
Requires-Dist: walkabout
Requires-Dist: pytz
Requires-Dist: unidecode
Provides-Extra: docs
Requires-Dist: Sphinx (>=1.3.5); extra == 'docs'
Requires-Dist: repoze.sphinx.autointerface; extra == 'docs'
Provides-Extra: i18n
Requires-Dist: Babel; extra == 'i18n'
Requires-Dist: transifex-client; extra == 'i18n'
Requires-Dist: lingua (<2.0); extra == 'i18n'
Provides-Extra: testing
Requires-Dist: nose; extra == 'testing'
Requires-Dist: coverage; extra == 'testing'
Requires-Dist: mock; extra == 'testing'
Requires-Dist: tox; extra == 'testing'
